CHANGES.txt
MANIFEST.in
README.rst
requirements.txt
setup.py
leetchi/__init__.py
leetchi/api.py
leetchi/base.py
leetchi/compat.py
leetchi/exceptions.py
leetchi/fields.py
leetchi/query.py
leetchi/resources.py
leetchi/signals.py
leetchi/utils.py
python_leetchi.egg-info/PKG-INFO
python_leetchi.egg-info/SOURCES.txt
python_leetchi.egg-info/dependency_links.txt
python_leetchi.egg-info/not-zip-safe
python_leetchi.egg-info/requires.txt
python_leetchi.egg-info/top_level.txt
tests/__init__.py
tests/resources.py
tests/settings.py
tests/test_api.py
tests/test_contributions.py
tests/test_users.py
tests/test_wallets.py