Metadata-Version: 1.1
Name: python-leetchi
Version: 0.3.10
Summary: Leetchi API implementation in Python
Home-page: http://github.com/thoas/python-leetchi
Author: Florent Messa
Author-email: florent.messa@gmail.com
License: UNKNOWN
Keywords: leetchi api rest users wallets contributions
Platform: UNKNOWN
Classifier: Intended Audience :: Developers
Classifier: License :: OSI Approved :: MIT License
Classifier: Natural Language :: English
Classifier: Operating System :: OS Independent
Classifier: Programming Language :: Python
Classifier: Topic :: Software Development :: Libraries :: Python Modules
Classifier: Programming Language :: Python :: 3
